trilent/__init__.py
trilent/Animations/__init__.py
trilent/Animations/animation.py
trilent/Animations/easing_function_generator.py
trilent/Animations/easing_functions.py
trilent/Animations/helpers.py
trilent/Animations/initials_generator.py
trilent/Animations/list_generator.py
trilent/FlexComputer/__init__.py
trilent/FlexComputer/center_alignment.py
trilent/FlexComputer/end_alignment.py
trilent/FlexComputer/general.py
trilent/FlexComputer/main.py
trilent/FlexComputer/start_alignment.py
trilent/Utility/__init__.py
trilent/Utility/color.py
trilent/Utility/color_gradients.py
trilent/Utility/misc.py
trilent/Utility/orientation.py
trilent/Utility/other_gradients.py
trilent/Utility/property_manager.py
trilent/Utility/qss_reloader.py
trilent/Utility/unit.py
trilent/Widgets/__init__.py
trilent/Widgets/box.py
trilent/Widgets/button.py
trilent/Widgets/canvas.py
trilent/Widgets/check_box.py
trilent/Widgets/entry.py
trilent/Widgets/frame.py
trilent/Widgets/image.py
trilent/Widgets/slider.py
trilent/Widgets/spacer.py
trilent/Widgets/switch.py
trilent/Widgets/text.py
trilent/Widgets/widget.py
trilent/Window/__init__.py
trilent/Window/window.py
trilent-2.3.4.8.dist-info/METADATA
trilent-2.3.4.8.dist-info/WHEEL
trilent-2.3.4.8.dist-info/top_level.txt
trilent-2.3.4.8.dist-info/RECORD
