Metadata-Version: 2.1
Name: trilent
Version: 2.3.4.8
Summary: Python GUI Framework.
Author: Schkimansky
Author-email: <ahmadchawla1432@gmail.com>
Keywords: python,gui,ui,framework,app,application,ui building,app development
Classifier: Development Status :: 1 - Planning
Classifier: Intended Audience :: Developers
Classifier: Programming Language :: Python :: 3
Classifier: Operating System :: Unix
Classifier: Operating System :: MacOS :: MacOS X
Classifier: Operating System :: Microsoft :: Windows
Requires-Dist: PyQt6
Requires-Dist: conversa
Requires-Dist: numpy
